nauta/__init__.py
nauta/__main__.py
nauta/cli.py
nauta/client.py
nauta/constants.py
nauta/database.py
nauta/models.py
nauta/secure.py
nauta/commands/account.py
nauta/commands/session.py
nauta-0.1.4.dist-info/METADATA
nauta-0.1.4.dist-info/WHEEL
nauta-0.1.4.dist-info/entry_points.txt
nauta-0.1.4.dist-info/licenses/LICENSE
nauta-0.1.4.dist-info/RECORD
