Metadata-Version: 2.4
Name: nauta
Version: 0.1.4
Summary: Línea de comandos para el nauta hogar Cuba
Project-URL: Homepage, https://github.com/raulodev/nauta
Project-URL: Issues, https://github.com/raulodev/nauta/issues
Author-email: Raúl Cobiellas <raulodev@gmail.com>
License-File: LICENSE
Classifier: License :: OSI Approved :: MIT License
Classifier: Operating System :: OS Independent
Classifier: Programming Language :: Python :: 3
Requires-Python: >=3.8
Requires-Dist: appdirs==1.4.4
Requires-Dist: beautifulsoup4==4.12.3
Requires-Dist: requests==2.32.4
Requires-Dist: typer==0.16.0
Requires-Dist: urllib3==1.26.18
